{
    "Version": "1.2",
    "Data": {
        "Source": "d:\\programming\\c++20\\ั++20\\helloworld.cppm",
        "ProvidedModule": "helloworld",
        "Includes": [],
        "ImportedModules": [],
        "ImportedHeaderUnits": [
            {
                "Header": "c:\\program files\\microsoft visual studio\\2022\\professional\\vc\\tools\\msvc\\14.38.33130\\include\\iostream",
                "BMI": "D:\\Programming\\C++20\\ะก++20\\x64\\Debug\\iostream_6B781489721B194F.ifc.dt"
            }
        ]
    }
}